jupyterjs/__init__.py
jupyterjs/_frontend.py
jupyterjs/_version.py
jupyterjs/example.py
jupyterjs/widget.py
jupyterjs/labextension/build_log.json
jupyterjs/labextension/package.json
jupyterjs/labextension/static/lib_index_js.453c9243aaf0fa301a73.js
jupyterjs/labextension/static/lib_index_js.453c9243aaf0fa301a73.js.map
jupyterjs/labextension/static/lib_plugin_js.9977e893f9f06feb6e14.js
jupyterjs/labextension/static/lib_plugin_js.9977e893f9f06feb6e14.js.map
jupyterjs/labextension/static/lib_widget_js.8660ea75f4e479190d59.js
jupyterjs/labextension/static/lib_widget_js.8660ea75f4e479190d59.js.map
jupyterjs/labextension/static/remoteEntry.e0a747120fc93ec0d983.js
jupyterjs/labextension/static/remoteEntry.e0a747120fc93ec0d983.js.map
jupyterjs/labextension/static/style.js
jupyterjs/labextension/static/vendors-node_modules_css-loader_dist_runtime_api_js-node_modules_jquery_dist_jquery_js-node_m-c60908.757d9bd32c76b40dca43.js
jupyterjs/labextension/static/vendors-node_modules_css-loader_dist_runtime_api_js-node_modules_jquery_dist_jquery_js-node_m-c60908.757d9bd32c76b40dca43.js.map
jupyterjs/labextension/static/vendors-node_modules_on-change_index_js.dc7d1240ed048441b282.js
jupyterjs/labextension/static/vendors-node_modules_on-change_index_js.dc7d1240ed048441b282.js.map
jupyterjs/nbextension/extension.js
jupyterjs/nbextension/index.js
jupyterjs/nbextension/index.js.LICENSE.txt
jupyterjs/nbextension/index.js.map
jupyterjs/tests/__init__.py
jupyterjs/tests/conftest.py
jupyterjs/tests/test_example.py
jupyterjs/tests/test_nbextension_path.py
jupyterjs-0.1.0.dev1.data/data/share/jupyter/labextensions/jupyterjs/build_log.json
jupyterjs-0.1.0.dev1.data/data/share/jupyter/labextensions/jupyterjs/package.json
jupyterjs-0.1.0.dev1.data/data/share/jupyter/labextensions/jupyterjs/static/lib_index_js.453c9243aaf0fa301a73.js
jupyterjs-0.1.0.dev1.data/data/share/jupyter/labextensions/jupyterjs/static/lib_index_js.453c9243aaf0fa301a73.js.map
jupyterjs-0.1.0.dev1.dist-info/METADATA
jupyterjs-0.1.0.dev1.dist-info/WHEEL
jupyterjs-0.1.0.dev1.dist-info/licenses/LICENSE.txt
jupyterjs-0.1.0.dev1.dist-info/RECORD
